nonebot_plugin_agent/__init__.py
nonebot_plugin_agent/action/__init__.py
nonebot_plugin_agent/action/base.py
nonebot_plugin_agent/base.py
nonebot_plugin_agent/config.py
nonebot_plugin_agent/llm/__init__.py
nonebot_plugin_agent/llm/base.py
nonebot_plugin_agent/llm/openai.py
nonebot_plugin_agent-0.0.1.dist-info/LICENSE
nonebot_plugin_agent-0.0.1.dist-info/METADATA
nonebot_plugin_agent-0.0.1.dist-info/WHEEL
nonebot_plugin_agent-0.0.1.dist-info/RECORD
