Metadata-Version: 2.1
Name: nonebot-plugin-agent
Version: 0.0.1
Summary: A Agent shceduling nonebot2 plugin via user natural language inpput
License: GPLv3
Author: Dobiichi-Origami
Author-email: 56953648+Dobiichi-Origami@users.noreply.github.com
Requires-Python: >=3.10,<4.0
Classifier: License :: Other/Proprietary License
Classifier: Programming Language :: Python :: 3
Classifier: Programming Language :: Python :: 3.10
Classifier: Programming Language :: Python :: 3.11
Requires-Dist: nonebot2 (>=2.1.0,<3.0.0)
Requires-Dist: openai (>=0.28.0,<0.29.0)
